textvecpy/__init__.py
textvecpy/greet.py
textvecpy-0.0.1.dist-info/METADATA
textvecpy-0.0.1.dist-info/WHEEL
textvecpy-0.0.1.dist-info/top_level.txt
textvecpy-0.0.1.dist-info/RECORD
